docc/__init__.py
docc/_sdfg.cpython-311-x86_64-linux-gnu.so
docc/ast_parser.py
docc/ast_utils.py
docc/compiled_sdfg.py
docc/convolution.py
docc/expression_visitor.py
docc/libarg_capture_io.a
docc/libdaisy_rtl.a
docc/linear_algebra.py
docc/onnx_ops.py
docc/include/daisy_rtl/arg_capture_io.h
docc/include/daisy_rtl/base64.h
docc/include/daisy_rtl/daisy_rtl.h
docc/include/daisy_rtl/global_tenstorrent_init.h
docc/include/daisy_rtl/primitive_types.h
docc_compiler.libs/libboost_graph-0f1a0e27.so.1.66.0
docc_compiler.libs/libboost_regex-2b30dfd4.so.1.66.0
docc_compiler.libs/libbrotlicommon-6ce2a53c.so.1.0.6
docc_compiler.libs/libbrotlidec-811d1be3.so.1.0.6
docc_compiler.libs/libcom_err-730ca923.so.2.1
docc_compiler.libs/libcrypt-52aca757.so.1.1.0
docc_compiler.libs/libcrypto-bdaed0ea.so.1.1.1k
docc_compiler.libs/libcurl-14a7698c.so.4.5.0
docc_compiler.libs/libgmp-d944b113.so.10.3.2
docc_compiler.libs/libgssapi_krb5-323bbd21.so.2.2
docc_compiler.libs/libicudata-05640f77.so.60.3
docc_compiler.libs/libicui18n-4fcc01ea.so.60.3
docc_compiler.libs/libicuuc-14201aad.so.60.3
docc_compiler.libs/libidn2-2f4a5893.so.0.3.6
docc_compiler.libs/libisl-6caf0409.so.23.4.0
docc_compiler.libs/libk5crypto-9a74ff38.so.3.1
docc_compiler.libs/libkeyutils-2777d33d.so.1.6
docc_compiler.libs/libkrb5-a55300e8.so.3.3
docc_compiler.libs/libkrb5support-e6594cfc.so.0.1
docc_compiler.libs/liblber-2-d20824ef.4.so.2.10.9
docc_compiler.libs/libldap-2-cea2a960.4.so.2.10.9
docc_compiler.libs/libnghttp2-39367a22.so.14.17.0
docc_compiler.libs/libpcre2-8-516f4c9d.so.0.7.1
docc_compiler.libs/libpsl-99becdd3.so.5.3.1
docc_compiler.libs/libsasl2-7de4d792.so.3.0.0
docc_compiler.libs/libselinux-d0805dcb.so.1
docc_compiler.libs/libssh-9f6d898c.so.4.8.7
docc_compiler.libs/libssl-60250281.so.1.1.1k
docc_compiler.libs/libunistring-05abdd40.so.2.1.0
include/daisy_rtl/arg_capture_io.h
include/daisy_rtl/base64.h
include/daisy_rtl/daisy_rtl.h
docc_compiler-0.0.2.dist-info/METADATA
docc_compiler-0.0.2.dist-info/WHEEL
docc_compiler-0.0.2.dist-info/RECORD
docc_compiler-0.0.2.dist-info/sboms/auditwheel.cdx.json
