Metadata-Version: 2.2
Name: docc-compiler
Version: 0.0.2
Summary: A JIT compiler for Numpy-based Python programs and bindings for stateful dataflow multigraphs (SDFG).
Author-Email: Daisytuner <hello@daisytuner.com>
Maintainer-Email: Daisytuner <hello@daisytuner.com>
License: BSD-3-Clause
Classifier: Development Status :: 4 - Beta
Classifier: Intended Audience :: Developers
Classifier: Intended Audience :: Science/Research
Classifier: License :: OSI Approved :: BSD License
Classifier: Operating System :: POSIX :: Linux
Classifier: Operating System :: MacOS
Classifier: Programming Language :: Python :: 3
Classifier: Programming Language :: Python :: 3.11
Classifier: Programming Language :: Python :: 3.12
Classifier: Programming Language :: Python :: 3.13
Classifier: Programming Language :: Python :: 3.14
Classifier: Programming Language :: C++
Classifier: Topic :: Scientific/Engineering
Classifier: Topic :: Software Development :: Compilers
Project-URL: Homepage, https://daisytuner.com
Project-URL: Documentation, https://docs.daisytuner.com
Project-URL: Repository, https://github.com/daisytuner/docc
Project-URL: Issues, https://github.com/daisytuner/docc/issues
Requires-Python: >=3.11
Requires-Dist: numpy>=1.19.0
Requires-Dist: scipy>=1.7.0
